olostep/.DS_Store
olostep/__init__.py
olostep/_log.py
olostep/backend/api_endpoints.py
olostep/backend/caller.py
olostep/backend/transport.py
olostep/backend/transport_protocol.py
olostep/clients/async_client.py
olostep/clients/sync_client.py
olostep/config.py
olostep/errors.py
olostep/frontend/_id_storage.py
olostep/frontend/batch_menu.py
olostep/frontend/client_state.py
olostep/frontend/crawl_menu.py
olostep/frontend/input_coersion.py
olostep/frontend/retrieve_menu.py
olostep/frontend/scrape_menu.py
olostep/frontend/sitemap_menu.py
olostep/models/base.py
olostep/models/request.py
olostep/models/response.py
olostep-0.9.0.dist-info/licenses/LICENSE
olostep-0.9.0.dist-info/METADATA
olostep-0.9.0.dist-info/WHEEL
olostep-0.9.0.dist-info/RECORD
