Metadata-Version: 2.4
Name: olostep
Version: 0.9.0
Summary: Olostep Python SDK - Programmatic access to the web
License-File: LICENSE
Author: Olostep Team
Author-email: team@olostep.com
Requires-Python: >=3.11,<3.14
Classifier: Programming Language :: Python :: 3
Classifier: Programming Language :: Python :: 3.11
Classifier: Programming Language :: Python :: 3.12
Classifier: Programming Language :: Python :: 3.13
Requires-Dist: httpx[http2] (>=0.28.1,<0.29.0)
Requires-Dist: pydantic (>=2.11.3,<3.0.0)
